LICENSE.txt
MANIFEST.in
README.md
setup.py
benchmarks/bottle/benchmark.py
benchmarks/fastapi/benchmark.py
benchmarks/flask/benchmark.py
benchmarks/japronto/benchmark.py
benchmarks/ludicrous/benchmark.py
benchmarks/nodejs/benchmark.js
docs/EXAMPLES.md
include/jsmn.h
include/json.h
include/server.h
include/urlnode.h
lib/mongoose/.clang-format
lib/mongoose/.git
lib/mongoose/LICENSE
lib/mongoose/Makefile
lib/mongoose/README.md
lib/mongoose/mongoose.c
lib/mongoose/mongoose.h
lib/mongoose/.github/issue_template.md
lib/mongoose/.github/workflows/cifuzz.yml
lib/mongoose/.github/workflows/test.yml
lib/mongoose/docs/README.md
lib/mongoose/docs/images/mg_commalist.svg
lib/mongoose/docs/images/mg_http_get_request_len.svg
lib/mongoose/docs/images/mg_http_message.svg
lib/mongoose/docs/images/mg_http_next_multipart.svg
lib/mongoose/docs/images/mg_http_part.svg
lib/mongoose/docs/images/mg_http_reply.svg
lib/mongoose/docs/images/mg_iobuf.svg
lib/mongoose/docs/images/mg_iobuf_add1.svg
lib/mongoose/docs/images/mg_iobuf_add2.svg
lib/mongoose/docs/images/mg_iobuf_del.svg
lib/mongoose/examples/captive-dns-server/Makefile
lib/mongoose/examples/captive-dns-server/README.md
lib/mongoose/examples/captive-dns-server/main.c
lib/mongoose/examples/device-dashboard/Makefile
lib/mongoose/examples/device-dashboard/README.md
lib/mongoose/examples/device-dashboard/ca.pem
lib/mongoose/examples/device-dashboard/main.c
lib/mongoose/examples/device-dashboard/net.c
lib/mongoose/examples/device-dashboard/packed_fs.c
lib/mongoose/examples/device-dashboard/screenshots/dashboard.png
lib/mongoose/examples/device-dashboard/screenshots/login.png
lib/mongoose/examples/device-dashboard/web_root/index.html
lib/mongoose/examples/device-dashboard/web_root/main.js
lib/mongoose/examples/device-dashboard/web_root/preact.min.js
lib/mongoose/examples/device-dashboard/web_root/style.css
lib/mongoose/examples/device-dashboard/web_root/user.png
lib/mongoose/examples/embedded-filesystem/Makefile
ludicrous.egg-info/PKG-INFO
ludicrous.egg-info/SOURCES.txt
ludicrous.egg-info/dependency_links.txt
ludicrous.egg-info/top_level.txt
