Metadata-Version: 2.1
Name: ludicrous
Version: 0.3.0
Summary: ludicrous speed JSON API framework for Python
Home-page: https://github.com/joshiemoore/ludicrous/
Author: Joshua Moore
Author-email: jxm5210@g.rit.edu
License: GPLv2
License-File: LICENSE.txt
